israeli_law_amender/Amd_example.py
israeli_law_amender/Generalized_amd_flow.py
israeli_law_amender/__init__.py
israeli_law_amender/config.py
israeli_law_amender/core.py
israeli_law_amender/helpers.py
israeli_law_amender/json_to_html.py
israeli_law_amender/laws_amending_script.py
israeli_law_amender/logger.py
israeli_law_amender/product_flow_helpers.py
israeli_law_amender/CSV to json/csv_to_json.py
israeli_law_amender/CSV to json/generate_changes_json.py
israeli_law_amender/CSV to json/generate_simple_857.py
israeli_law_amender/CSV to json/generate_version_857.py
israeli_law_amender/CSV to json/verify_changes_json.py
israeli_law_amender/CSV to json/verify_json.py
israeli_law_amender/CSV to json/verify_json_output.py
israeli_law_amender/Renaming/fix_csv_properly.py
israeli_law_amender/Renaming/rename_json_files_with_lawid.py
israeli_law_amender/Wiki to txt/check_law_files.py
israeli_law_amender/Wiki to txt/wikiload.py
israeli_law_amender/Wiki to txt/wikiload_v2.py
israeli_law_amender/Wiki_txt_to_json/txt_to_json_v2.py
israeli_law_amender/validation/__init__.py
israeli_law_amender/validation/extract_file_names.py
israeli_law_amender/validation/layer1_validation.py
israeli_law_amender/validation/layer2_validation.py
israeli_law_amender/validation/layer3_validation.py
israeli_law_amender-1.0.3.dist-info/licenses/LICENSE
israeli_law_amender-1.0.3.dist-info/METADATA
israeli_law_amender-1.0.3.dist-info/WHEEL
israeli_law_amender-1.0.3.dist-info/entry_points.txt
israeli_law_amender-1.0.3.dist-info/top_level.txt
israeli_law_amender-1.0.3.dist-info/RECORD
