Metadata-Version: 2.4
Name: israeli-law-amender
Version: 1.0.3
Summary: A Python package for processing and amending Israeli laws using AI
Home-page: https://github.com/Double-N-A/israeli-law-amender
Author: Hila Peled, Nitzan Naimi, Ohad Nahari, Ran Cohen
Author-email: hila.peled@mail.huji.ac.il, nitzan.naimi@mail.huji.ac.il, ohad.nahar@mail.huji.ac.il, ran.cohen@mail.huji.ac.il
Classifier: Development Status :: 4 - Beta
Classifier: Intended Audience :: Legal Industry
Classifier: License :: OSI Approved :: MIT License
Classifier: Operating System :: OS Independent
Classifier: Programming Language :: Python :: 3
Classifier: Programming Language :: Python :: 3.8
Classifier: Programming Language :: Python :: 3.9
Classifier: Programming Language :: Python :: 3.10
Classifier: Programming Language :: Python :: 3.11
Classifier: Topic :: Text Processing :: Linguistic
Classifier: Topic :: Software Development :: Libraries :: Python Modules
Requires-Python: >=3.8
License-File: LICENSE
Requires-Dist: google-generativeai>=0.3.0
Requires-Dist: google-api-core>=2.0.0
Requires-Dist: pandas>=1.3.0
Requires-Dist: PyYAML>=6.0
Requires-Dist: thefuzz[speedup]>=0.19.0
Requires-Dist: sentence-transformers>=2.2.0
Dynamic: author
Dynamic: author-email
Dynamic: classifier
Dynamic: description
Dynamic: description-content-type
Dynamic: home-page
Dynamic: license-file
Dynamic: requires-dist
Dynamic: requires-python
Dynamic: summary
